{
  "indexes": [
    {
      "collectionGroup": "cards",
      "queryScope": "COLLECTION_GROUP",
      "fields": [
        {
          "fieldPath": "category",
          "order": "ASCENDING"
        },
        {
          "fieldPath": "title",
          "order": "ASCENDING"
        }
      ]
    },
    {
      "collectionGroup": "posts",
      "queryScope": "COLLECTION_GROUP",
      "fields": [
        {
          "fieldPath": "country",
          "order": "ASCENDING"
        },
        {
          "fieldPath": "published",
          "order": "ASCENDING"
        }
      ]
    },
    {
      "collectionGroup": "posts",
      "queryScope": "COLLECTION_GROUP",
      "fields": [
        {
          "fieldPath": "id",
          "order": "ASCENDING"
        },
        {
          "fieldPath": "published",
          "order": "ASCENDING"
        }
      ]
    },
    {
      "collectionGroup": "posts",
      "queryScope": "COLLECTION_GROUP",
      "fields": [
        {
          "fieldPath": "id",
          "order": "ASCENDING"
        },
        {
          "fieldPath": "visibility",
          "order": "ASCENDING"
        }
      ]
    }
  ],
  "fieldOverrides": [
    {
      "collectionGroup": "cards",
      "fieldPath": "category",
      "ttl": false,
      "indexes": [
        {
          "order": "ASCENDING",
          "queryScope": "COLLECTION"
        },
        {
          "order": "DESCENDING",
          "queryScope": "COLLECTION"
        },
        {
          "arrayConfig": "CONTAINS",
          "queryScope": "COLLECTION"
        },
        {
          "order": "ASCENDING",
          "queryScope": "COLLECTION_GROUP"
        }
      ]
    },
    {
      "collectionGroup": "cards",
      "fieldPath": "id",
      "ttl": false,
      "indexes": [
        {
          "order": "ASCENDING",
          "queryScope": "COLLECTION"
        },
        {
          "order": "DESCENDING",
          "queryScope": "COLLECTION"
        },
        {
          "arrayConfig": "CONTAINS",
          "queryScope": "COLLECTION"
        },
        {
          "order": "ASCENDING",
          "queryScope": "COLLECTION_GROUP"
        }
      ]
    },
    {
      "collectionGroup": "posts",
      "fieldPath": "id",
      "ttl": false,
      "indexes": [
        {
          "order": "ASCENDING",
          "queryScope": "COLLECTION"
        },
        {
          "order": "DESCENDING",
          "queryScope": "COLLECTION"
        },
        {
          "arrayConfig": "CONTAINS",
          "queryScope": "COLLECTION"
        },
        {
          "order": "ASCENDING",
          "queryScope": "COLLECTION_GROUP"
        }
      ]
    },
    {
      "collectionGroup": "posts",
      "fieldPath": "published",
      "ttl": false,
      "indexes": [
        {
          "order": "ASCENDING",
          "queryScope": "COLLECTION"
        },
        {
          "order": "DESCENDING",
          "queryScope": "COLLECTION"
        },
        {
          "arrayConfig": "CONTAINS",
          "queryScope": "COLLECTION"
        },
        {
          "order": "ASCENDING",
          "queryScope": "COLLECTION_GROUP"
        }
      ]
    }
  ]
}
